k3s_local_docker/__init__.py
k3s_local_docker/commands/__init__.py
k3s_local_docker/commands/compose.py
k3s_local_docker/commands/copy_kubeconfig.py
k3s_local_docker/commands/fix_owner.py
k3s_local_docker/commands/wait_for_resources.py
k3s_local_docker/config.py
k3s_local_docker/generate.py
k3s_local_docker/monkeypatch.py
k3s_local_docker/templates/config/config.yaml.j2
k3s_local_docker/templates/config/registries.yaml.j2
k3s_local_docker/templates/docker-compose.yml.j2
k3s_local_docker/utils.py
k3s_local_docker-0.1.0a1.dist-info/LICENSE
k3s_local_docker-0.1.0a1.dist-info/METADATA
k3s_local_docker-0.1.0a1.dist-info/WHEEL
k3s_local_docker-0.1.0a1.dist-info/entry_points.txt
k3s_local_docker-0.1.0a1.dist-info/RECORD
